outfit418_backup_ratting/__init__.py
outfit418_backup_ratting/apps.py
outfit418_backup_ratting/auth_hooks.py
outfit418_backup_ratting/forms.py
outfit418_backup_ratting/models.py
outfit418_backup_ratting/provider.py
outfit418_backup_ratting/signals.py
outfit418_backup_ratting/tasks.py
outfit418_backup_ratting/urls.py
outfit418_backup_ratting/utils.py
outfit418_backup_ratting/views.py
outfit418_backup_ratting/management/commands/418_login_update.py
outfit418_backup_ratting/management/commands/418_ts_update.py
outfit418_backup_ratting/migrations/0001_initial.py
outfit418_backup_ratting/migrations/0002_general.py
outfit418_backup_ratting/migrations/0003_characterauditlogindata.py
outfit418_backup_ratting/migrations/0004_alter_general_options.py
outfit418_backup_ratting/migrations/0005_eventbackup_eventmemberbackup.py
outfit418_backup_ratting/migrations/__init__.py
outfit418_backup_ratting/templates/outfit418_backup_ratting/audit.html
outfit418_backup_ratting/templates/outfit418_backup_ratting/event_backups.html
outfit418_backup_ratting/templates/outfit418_backup_ratting/find_jeremy.html
outfit418_backup_ratting/templates/outfit418_backup_ratting/index.html
outfit418_backup_ratting/templatetags/__init__.py
outfit418_backup_ratting/templatetags/outfit_tags.py
outfit418_backup_ratting-0.7.0.dist-info/LICENSE
outfit418_backup_ratting-0.7.0.dist-info/WHEEL
outfit418_backup_ratting-0.7.0.dist-info/METADATA
outfit418_backup_ratting-0.7.0.dist-info/RECORD
