Metadata-Version: 2.3
Name: outfit418_backup_ratting
Version: 0.7.0
Summary: Backup for Outfit418 data
Keywords: allianceauth,allianceauth_pve,outfit418,eveonline
Author-email: Matteo Ghia <matteo.ghia@yahoo.it>
Requires-Python: ~=3.8
Requires-Dist: allianceauth~=4.0
Requires-Dist: allianceauth_pve~=1.10
Project-URL: Changelog, https://github.com/Maestro-Zacht/outfit418-backup-ratting/releases
Project-URL: Homepage, https://github.com/Maestro-Zacht/outfit418-backup-ratting
Project-URL: Source, https://github.com/Maestro-Zacht/outfit418-backup-ratting
Project-URL: Tracker, https://github.com/Maestro-Zacht/outfit418-backup-ratting/issues
